stilpy/__init__.py
stilpy/timegaps.py
stilpy/timeinterval.py
stilpy-1.0.1.dist-info/AUTHORS.rst
stilpy-1.0.1.dist-info/LICENSE
stilpy-1.0.1.dist-info/METADATA
stilpy-1.0.1.dist-info/WHEEL
stilpy-1.0.1.dist-info/top_level.txt
stilpy-1.0.1.dist-info/RECORD
