Metadata-Version: 2.1
Name: stilpy
Version: 1.0.1
Summary: Stilpy creates time intervals from records and manage them for you.
Home-page: https://github.com/fesanmar/stilpy
Author: Felipe Santa-Cruz
Author-email: fesanmar@gmail.com
License: MIT license
Keywords: stilpy sorts time records to create time intervals iterators
Platform: UNKNOWN
Classifier: Development Status :: 3 - Alpha
Classifier: Intended Audience :: Developers
Classifier: License :: OSI Approved :: MIT License
Classifier: Natural Language :: English
Classifier: Programming Language :: Python :: 3
Classifier: Programming Language :: Python :: 3.5
Classifier: Programming Language :: Python :: 3.6
Classifier: Programming Language :: Python :: 3.7
Classifier: Programming Language :: Python :: 3.8
Classifier: Programming Language :: Python :: 3.10
Classifier: Programming Language :: Python :: 3.12
Requires-Python: >=3.5
